README.rst
setup.py
utc/__init__.py
utc.egg-info/PKG-INFO
utc.egg-info/SOURCES.txt
utc.egg-info/dependency_links.txt
utc.egg-info/top_level.txt