Metadata-Version: 1.0
Name: utc
Version: 0.0.1
Summary: A tiny library for working with UTC time.
Home-page: http://bits.btubbs.com/utc
Author: Brent Tubbs
Author-email: brent.tubbs@gmail.com
License: UNKNOWN
Platform: UNKNOWN
